maptekblastlogic/__init__.py
maptekblastlogic/client.py
maptekblastlogic/errors.py
maptekblastlogic/types.py
maptekblastlogic/api/__init__.py
maptekblastlogic/api/backfilling_entries/__init__.py
maptekblastlogic/api/backfilling_entries/batch_create_backfilling_entries.py
maptekblastlogic/api/backfilling_entries/batch_get_backfilling_entries.py
maptekblastlogic/api/backfilling_entries/batch_update_backfilling_entries.py
maptekblastlogic/api/backfilling_entries/create_backfilling_entry.py
maptekblastlogic/api/backfilling_entries/get_backfilling_entries_by_blast_id.py
maptekblastlogic/api/backfilling_entries/get_backfilling_entries_by_hole_id.py
maptekblastlogic/api/backfilling_entries/get_backfilling_entry_by_id.py
maptekblastlogic/api/backfilling_entries/update_backfilling_entry.py
maptekblastlogic/api/blasts/__init__.py
maptekblastlogic/api/blasts/blast_search.py
maptekblastlogic/api/blasts/get_blast_by_id.py
maptekblastlogic/api/charge_plans/__init__.py
maptekblastlogic/api/charge_plans/get_charge_plan_by_hole_id.py
maptekblastlogic/api/charge_plans/get_charge_plans_by_blast_id.py
maptekblastlogic/api/crews/__init__.py
maptekblastlogic/api/crews/create_crew.py
maptekblastlogic/api/crews/get_crews.py
maptekblastlogic/api/crews/update_crew.py
maptekblastlogic/api/deck_products/__init__.py
maptekblastlogic/api/deck_products/get_deck_products.py
maptekblastlogic/api/dipping_entries/__init__.py
maptekblastlogic/api/dipping_entries/batch_create_dipping_entries.py
maptekblastlogic/api/dipping_entries/batch_get_dipping_entries.py
maptekblastlogic/api/dipping_entries/batch_update_dipping_entries.py
maptekblastlogic/api/dipping_entries/create_dipping_entry.py
maptekblastlogic/api/dipping_entries/get_dipping_entries_by_blast_id.py
maptekblastlogic/api/dipping_entries/get_dipping_entries_by_hole_id.py
maptekblastlogic/api/dipping_entries/get_dipping_entry_by_id.py
maptekblastlogic/api/dipping_entries/update_dipping_entry.py
maptekblastlogic/api/holes/__init__.py
maptekblastlogic-0.8.dist-info/METADATA
maptekblastlogic-0.8.dist-info/WHEEL
maptekblastlogic-0.8.dist-info/RECORD
