Metadata-Version: 2.3
Name: maptekblastlogic
Version: 0.8
Summary: Client for Maptek BlastLogic server.
License: Maptek End User License Agreement
Classifier: License :: Other/Proprietary License
Classifier: Programming Language :: Python :: 3
Requires-Python: <4,>=3.8
Requires-Dist: attrs>=21.3.0
Requires-Dist: httpx<0.28.0,>=0.20.0
Requires-Dist: python-dateutil<3,>=2.8.0
